<?xml version = '1.0' encoding = 'UTF-8'?>
<FKIndexAssociation class="oracle.dbtools.crest.model.design.relational.FKIndexAssociation" directorySegmentName="seg_0" id="524A6E50-25D0-724A-BAE0-3BF92FADFAF1" containerWithKeyObject="D09D46D9-0EF8-EB77-FA53-41A814B9F57B" localFKIndex="AB511C90-A1FD-5C71-8D71-F1A88A7AED2A" name="STATUS_LOCACAO_LOCACAO_FK">
<createdBy>maite</createdBy>
<createdTime>2019-10-27 23:14:22 UTC</createdTime>
<ownerDesignName>NAC SPIDERPIGS</ownerDesignName>
<referredTableLongName>LOCACAO</referredTableLongName>
<deleteRule>NO ACTION</deleteRule>
<referredTableID>FF1C3E97-2DED-3E96-D626-A2036397C08D</referredTableID>
<keyObject>886DF389-23D0-0F54-E462-5A7D9601D4CC</keyObject>
<referredKeyID>886DF389-23D0-0F54-E462-5A7D9601D4CC</referredKeyID>
<mandatory>true</mandatory>
<refColNames>LOC_ID</refColNames>
<transferable>true</transferable>
<rely>false</rely>
<columnDependencyConstraintGenerateInDDL>true</columnDependencyConstraintGenerateInDDL>
</FKIndexAssociation>